taky/__init__.py
taky/__main__.py
taky/util.py
taky/cot/__init__.py
taky/cot/client.py
taky/cot/router.py
taky/cot/server.py
taky/cot/teams.py
taky/cot/models/__init__.py
taky/cot/models/event.py
taky/cot/models/geochat.py
taky/cot/models/point.py
taky/cot/models/takuser.py
taky-0.4.dist-info/LICENSE
taky-0.4.dist-info/METADATA
taky-0.4.dist-info/WHEEL
taky-0.4.dist-info/entry_points.txt
taky-0.4.dist-info/top_level.txt
taky-0.4.dist-info/RECORD
