Metadata-Version: 2.1
Name: taky
Version: 0.4
Summary: A simple TAK server and COT router
Home-page: https://github.com/tkuester/taky
Author: Tim K
Author-email: tpkuester@gmail.com
License: UNKNOWN
Platform: UNKNOWN
Classifier: Topic :: Communications
Classifier: Development Status :: 3 - Alpha
Classifier: Programming Language :: Python :: 3.7
Classifier: License :: OSI Approved :: MIT License
Requires-Python: >=3.6
Requires-Dist: dateutils
Requires-Dist: lxml
